pytest_webtestpilot/__init__.py
pytest_webtestpilot/plugin.py
pytest_webtestpilot-0.1.1.dist-info/METADATA
pytest_webtestpilot-0.1.1.dist-info/WHEEL
pytest_webtestpilot-0.1.1.dist-info/entry_points.txt
pytest_webtestpilot-0.1.1.dist-info/top_level.txt
pytest_webtestpilot-0.1.1.dist-info/RECORD
