Metadata-Version: 2.4
Name: pytest-webtestpilot
Version: 0.1.1
Summary: Pytest plugin for running WebTestPilot JSON tests
Classifier: Framework :: Pytest
Requires-Python: >=3.12
Requires-Dist: pytest>=9.0.2
Requires-Dist: playwright>=1.53.0
Requires-Dist: pydantic>=2.11.7
Requires-Dist: webtestpilot>=0.1.8
